spireg_c1101/__init__.py
spireg_c1101/__version__.py
spireg_c1101/configuration_register.py
spireg_c1101/spi_address_space.py
spireg_c1101/status_register.py
spireg_c1101-0.1.0.dist-info/LICENSE
spireg_c1101-0.1.0.dist-info/WHEEL
spireg_c1101-0.1.0.dist-info/METADATA
spireg_c1101-0.1.0.dist-info/RECORD
