Metadata-Version: 2.3
Name: spireg_c1101
Version: 0.1.0
Summary: SPIReg-C1101 provides predefined registers for the CC1101 chip. 
Author-email: Daniël van den Berg <daniel@dmvandenberg.nl>
Classifier: License :: OSI Approved :: GNU General Public License v3 or later (GPLv3+)
Classifier: License :: Other/Proprietary License
Requires-Dist: spireg>=0.1.3
Requires-Dist: flake8 ; extra == "dev"
Provides-Extra: dev
